pyremotedict-0.1.0.dist-info/licenses/LICENSE
remotedict/__init__.py
remotedict/expiring_remotedict.py
remotedict/persistent_remotedict.py
remotedict/remotedict.py
pyremotedict-0.1.0.dist-info/METADATA
pyremotedict-0.1.0.dist-info/WHEEL
pyremotedict-0.1.0.dist-info/top_level.txt
pyremotedict-0.1.0.dist-info/RECORD
