Metadata-Version: 2.4
Name: pyRemoteDict
Version: 0.1.0
Summary: RemoteDict is a lightweight, in-memory key-value store server implemented in Python.
Home-page: https://github.com/technojo2000/RemoteDict
Author: TechnoJo
License: MIT License
Project-URL: Homepage, https://github.com/technojo2000/RemoteDict
Project-URL: Repository, https://github.com/technojo2000/RemoteDict
Requires-Python: >=3.7
License-File: LICENSE
Dynamic: home-page
Dynamic: license-file
Dynamic: requires-python
